.gitignore
.gitlab-ci.yml
CHANGELOG.md
CMakeLists.txt
COPYING
INSTALL
LICENSE.md
README.md
config.h.cmake
dune-geometry.pc.in
dune.module
pyproject.toml
setup.py
LICENSES/LicenseRef-GPL-2.0-only-with-DUNE-exception.txt
doc/CMakeLists.txt
doc/appl/CMakeLists.txt
doc/appl/refelements/CMakeLists.txt
doc/appl/refelements/SVG.readme
doc/appl/refelements/gg_hexahedron.png
doc/appl/refelements/gg_hexahedron.png.license
doc/appl/refelements/gg_hexahedron.svg
doc/appl/refelements/gg_hexahedron.svg.license
doc/appl/refelements/gg_hexahedron_edges.png
doc/appl/refelements/gg_hexahedron_edges.png.license
doc/appl/refelements/gg_hexahedron_edges.svg
doc/appl/refelements/gg_hexahedron_edges.svg.license
doc/appl/refelements/gg_line.png
doc/appl/refelements/gg_line.png.license
doc/appl/refelements/gg_line.svg
doc/appl/refelements/gg_line.svg.license
doc/appl/refelements/gg_prism.png
doc/appl/refelements/gg_prism.png.license
doc/appl/refelements/gg_prism.svg
doc/appl/refelements/gg_prism.svg.license
doc/appl/refelements/gg_prism_edges.png
doc/appl/refelements/gg_prism_edges.png.license
doc/appl/refelements/gg_prism_edges.svg
doc/appl/refelements/gg_prism_edges.svg.license
doc/appl/refelements/gg_pyramid.png
doc/appl/refelements/gg_pyramid.png.license
doc/appl/refelements/gg_pyramid.svg
doc/appl/refelements/gg_pyramid.svg.license
doc/appl/refelements/gg_pyramid_edges.png
doc/appl/refelements/gg_pyramid_edges.png.license
doc/appl/refelements/gg_pyramid_edges.svg
doc/appl/refelements/gg_pyramid_edges.svg.license
doc/appl/refelements/gg_quadrilateral.png
doc/appl/refelements/gg_quadrilateral.png.license
doc/appl/refelements/gg_quadrilateral.svg
doc/appl/refelements/gg_quadrilateral.svg.license
doc/appl/refelements/gg_tetrahedron.png
doc/appl/refelements/gg_tetrahedron.png.license
doc/appl/refelements/gg_tetrahedron.svg
doc/appl/refelements/gg_tetrahedron.svg.license
doc/appl/refelements/gg_tetrahedron_edges.png
doc/appl/refelements/gg_tetrahedron_edges.png.license
python/dune_geometry.egg-info/PKG-INFO
python/dune_geometry.egg-info/SOURCES.txt
python/dune_geometry.egg-info/dependency_links.txt
python/dune_geometry.egg-info/requires.txt
python/dune_geometry.egg-info/top_level.txt